[
  {
    "name": "2002",
    "artist": "Anne-Marie",
    "url": "https://openlist.ofxiv.qzz.io/d/kuake/music/2002%20-%20Anne-Marie.flac",
    "cover": "https://openlist.ofxiv.qzz.io/d/kuake/music/2002%20-%20Anne-Marie.jpg",
    "lrc": "https://openlist.ofxiv.qzz.io/d/kuake/music/2002%20-%20Anne-Marie.lrc",
    "filename": "2002 - Anne-Marie"
  },
  {
    "name": "Sakura",
    "artist": "R3HAB",
    "url": "https://openlist.ofxiv.qzz.io/d/kuake/music/Sakura%20-%20R3HAB.flac",
    "cover": "https://openlist.ofxiv.qzz.io/d/kuake/music/Sakura%20-%20R3HAB.jpg",
    "lrc": "https://openlist.ofxiv.qzz.io/d/kuake/music/Sakura%20-%20R3HAB.lrc",
    "filename": "Sakura - R3HAB"
  },
  {
    "name": "一样的月光",
    "artist": "徐佳莹",
    "url": "https://openlist.ofxiv.qzz.io/d/kuake/music/%E4%B8%80%E6%A0%B7%E7%9A%84%E6%9C%88%E5%85%89.flac",
    "cover": "https://openlist.ofxiv.qzz.io/d/kuake/music/pic/%E4%B8%80%E6%A0%B7%E7%9A%84%E6%9C%88%E5%85%89.jpg",
    "lrc": "https://openlist.ofxiv.qzz.io/d/kuake/music/lrc/%E4%B8%80%E6%A0%B7%E7%9A%84%E6%9C%88%E5%85%89.lrc",
    "filename": ""
  },
  {
    "name": "This Love",
    "artist": "Taylor Swift",
    "url": "https://openlist.ofxiv.qzz.io/d/kuake/music/This%20Love.flac",
    "cover": "https://openlist.ofxiv.qzz.io/d/kuake/music/pic/This%20Love.jpg",
    "lrc": "https://openlist.ofxiv.qzz.io/d/kuake/music/lrc/This%20Love.lrc",
    "filename": ""
  },
  {
    "name": "落 (花开花落日升日没)",
    "artist": "唐伯虎Annie",
    "url": "https://openlist.ofxiv.qzz.io/d/kuake/music/%E8%90%BD%20%28%E8%8A%B1%E5%BC%80%E8%8A%B1%E8%90%BD%E6%97%A5%E5%8D%87%E6%97%A5%E6%B2%A1%29.flac",
    "cover": "https://openlist.ofxiv.qzz.io/d/kuake/music/pic/%E8%90%BD%20%28%E8%8A%B1%E5%BC%80%E8%8A%B1%E8%90%BD%E6%97%A5%E5%8D%87%E6%97%A5%E6%B2%A1%29.jpg",
    "lrc": "https://openlist.ofxiv.qzz.io/d/kuake/music/lrc/%E8%90%BD%20%28%E8%8A%B1%E5%BC%80%E8%8A%B1%E8%90%BD%E6%97%A5%E5%8D%87%E6%97%A5%E6%B2%A1%29.lrc",
    "filename": ""
  },
  {
    "name": "爱不会绝迹",
    "artist": "林俊杰",
    "url": "https://openlist.ofxiv.qzz.io/d/kuake/music/%E7%88%B1%E4%B8%8D%E4%BC%9A%E7%BB%9D%E8%BF%B9%20-%20%E6%9E%97%E4%BF%8A%E6%9D%B0.flac",
    "cover": "https://openlist.ofxiv.qzz.io/d/kuake/music/%E7%88%B1%E4%B8%8D%E4%BC%9A%E7%BB%9D%E8%BF%B9%20-%20%E6%9E%97%E4%BF%8A%E6%9D%B0.jpg",
    "lrc": "https://openlist.ofxiv.qzz.io/d/kuake/music/%E7%88%B1%E4%B8%8D%E4%BC%9A%E7%BB%9D%E8%BF%B9%20-%20%E6%9E%97%E4%BF%8A%E6%9D%B0.lrc",
    "filename": "爱不会绝迹 - 林俊杰"
  },
  {
    "name": "不属于地球上的",
    "artist": "江楠江楠_",
    "url": "https://openlist.ofxiv.qzz.io/d/kuake/music/%E4%B8%8D%E5%B1%9E%E4%BA%8E%E5%9C%B0%E7%90%83%E4%B8%8A%E7%9A%84%20-%20%E6%B1%9F%E6%A5%A0%E6%B1%9F%E6%A5%A0_.flac",
    "cover": "https://openlist.ofxiv.qzz.io/d/kuake/music/%E4%B8%8D%E5%B1%9E%E4%BA%8E%E5%9C%B0%E7%90%83%E4%B8%8A%E7%9A%84%20-%20%E6%B1%9F%E6%A5%A0%E6%B1%9F%E6%A5%A0_.jpg",
    "lrc": "https://openlist.ofxiv.qzz.io/d/kuake/music/%E4%B8%8D%E5%B1%9E%E4%BA%8E%E5%9C%B0%E7%90%83%E4%B8%8A%E7%9A%84%20-%20%E6%B1%9F%E6%A5%A0%E6%B1%9F%E6%A5%A0_.lrc",
    "filename": "不属于地球上的 - 江楠江楠_"
  },
  {
    "name": "阳光下的星星",
    "artist": "金海心",
    "url": "https://openlist.ofxiv.qzz.io/d/kuake/music/%E9%98%B3%E5%85%89%E4%B8%8B%E7%9A%84%E6%98%9F%E6%98%9F%20-%20%E9%87%91%E6%B5%B7%E5%BF%83.flac",
    "cover": "https://openlist.ofxiv.qzz.io/d/kuake/music/%E9%98%B3%E5%85%89%E4%B8%8B%E7%9A%84%E6%98%9F%E6%98%9F%20-%20%E9%87%91%E6%B5%B7%E5%BF%83.jpg",
    "lrc": "https://openlist.ofxiv.qzz.io/d/kuake/music/%E9%98%B3%E5%85%89%E4%B8%8B%E7%9A%84%E6%98%9F%E6%98%9F%20-%20%E9%87%91%E6%B5%B7%E5%BF%83.lrc",
    "filename": "阳光下的星星 - 金海心"
  },
  {
    "name": "Paskui Tave",
    "artist": "Gjan",
    "url": "https://openlist.ofxiv.qzz.io/d/kuake/music/Paskui%20Tave%20-%20Gjan.flac",
    "cover": "https://openlist.ofxiv.qzz.io/d/kuake/music/Paskui%20Tave%20-%20Gjan.jpg",
    "lrc": "https://openlist.ofxiv.qzz.io/d/kuake/music/Paskui%20Tave%20-%20Gjan.lrc",
    "filename": "Paskui Tave - Gjan"
  },
  {
    "name": "小船摇",
    "artist": "雷丘Rachael",
    "url": "https://openlist.ofxiv.qzz.io/d/kuake/music/%E5%B0%8F%E8%88%B9%E6%91%87%20-%20%E9%9B%B7%E4%B8%98Rachael.flac",
    "cover": "https://openlist.ofxiv.qzz.io/d/kuake/music/%E5%B0%8F%E8%88%B9%E6%91%87%20-%20%E9%9B%B7%E4%B8%98Rachael.jpg",
    "lrc": "https://openlist.ofxiv.qzz.io/d/kuake/music/%E5%B0%8F%E8%88%B9%E6%91%87%20-%20%E9%9B%B7%E4%B8%98Rachael.lrc",
    "filename": "小船摇 - 雷丘Rachael"
  },
  {
    "name": "一格格",
    "artist": "卫兰",
    "url": "https://openlist.ofxiv.qzz.io/d/kuake/music/%E4%B8%80%E6%A0%BC%E6%A0%BC%20-%20%E5%8D%AB%E5%85%B0.flac",
    "cover": "https://openlist.ofxiv.qzz.io/d/kuake/music/%E4%B8%80%E6%A0%BC%E6%A0%BC%20-%20%E5%8D%AB%E5%85%B0.jpg",
    "lrc": "https://openlist.ofxiv.qzz.io/d/kuake/music/%E4%B8%80%E6%A0%BC%E6%A0%BC%20-%20%E5%8D%AB%E5%85%B0.lrc",
    "filename": "一格格 - 卫兰"
  },
  {
    "name": "u get me",
    "artist": "Gabriela Bee",
    "url": "https://openlist.ofxiv.qzz.io/d/kuake/music/u%20get%20me%20-%20Gabriela%20Bee.flac",
    "cover": "https://openlist.ofxiv.qzz.io/d/kuake/music/u%20get%20me%20-%20Gabriela%20Bee.jpg",
    "lrc": "https://openlist.ofxiv.qzz.io/d/kuake/music/u%20get%20me%20-%20Gabriela%20Bee.lrc",
    "filename": "u get me - Gabriela Bee"
  },
  {
    "name": "反正我也没什么关系",
    "artist": "庄东茹（豆芽鱼）",
    "url": "https://openlist.ofxiv.qzz.io/d/kuake/music/%E5%8F%8D%E6%AD%A3%E6%88%91%E4%B9%9F%E6%B2%A1%E4%BB%80%E4%B9%88%E5%85%B3%E7%B3%BB%20-%20%E5%BA%84%E4%B8%9C%E8%8C%B9%EF%BC%88%E8%B1%86%E8%8A%BD%E9%B1%BC%EF%BC%89.flac",
    "cover": "https://openlist.ofxiv.qzz.io/d/kuake/music/%E5%8F%8D%E6%AD%A3%E6%88%91%E4%B9%9F%E6%B2%A1%E4%BB%80%E4%B9%88%E5%85%B3%E7%B3%BB%20-%20%E5%BA%84%E4%B8%9C%E8%8C%B9%EF%BC%88%E8%B1%86%E8%8A%BD%E9%B1%BC%EF%BC%89.jpg",
    "lrc": "https://openlist.ofxiv.qzz.io/d/kuake/music/%E5%8F%8D%E6%AD%A3%E6%88%91%E4%B9%9F%E6%B2%A1%E4%BB%80%E4%B9%88%E5%85%B3%E7%B3%BB%20-%20%E5%BA%84%E4%B8%9C%E8%8C%B9%EF%BC%88%E8%B1%86%E8%8A%BD%E9%B1%BC%EF%BC%89.lrc",
    "filename": "反正我也没什么关系 - 庄东茹（豆芽鱼）"
  },
  {
    "name": "最好的我",
    "artist": "刘大拿/刘思达LOFTHESTAR",
    "url": "https://openlist.ofxiv.qzz.io/d/kuake/music/%E6%9C%80%E5%A5%BD%E7%9A%84%E6%88%91%20-%20%E5%88%98%E5%A4%A7%E6%8B%BF_%E5%88%98%E6%80%9D%E8%BE%BELOFTHESTAR.flac",
    "cover": "https://openlist.ofxiv.qzz.io/d/kuake/music/%E6%9C%80%E5%A5%BD%E7%9A%84%E6%88%91%20-%20%E5%88%98%E5%A4%A7%E6%8B%BF_%E5%88%98%E6%80%9D%E8%BE%BELOFTHESTAR.jpg",
    "lrc": "https://openlist.ofxiv.qzz.io/d/kuake/music/%E6%9C%80%E5%A5%BD%E7%9A%84%E6%88%91%20-%20%E5%88%98%E5%A4%A7%E6%8B%BF_%E5%88%98%E6%80%9D%E8%BE%BELOFTHESTAR.lrc",
    "filename": "最好的我 - 刘大拿_刘思达LOFTHESTAR"
  }
]
