[
  {
    "name": "To the Sky",
    "artist": "JigglePuff",
    "url": "https://openlist.ofxiv.qzz.io/d/kuake/music/To%20the%20Sky.mp3",
    "cover": "https://openlist.ofxiv.qzz.io/d/kuake/music/pic/To%20the%20Sky.jpg",
    "lrc": "https://openlist.ofxiv.qzz.io/d/kuake/music/lrc/To%20the%20Sky.lrc",
    "filename": ""
  },
  {
    "name": "爱丫爱丫",
    "artist": "By2",
    "url": "https://openlist.ofxiv.qzz.io/d/kuake/music/%E7%88%B1%E4%B8%AB%E7%88%B1%E4%B8%AB.flac",
    "cover": "https://openlist.ofxiv.qzz.io/d/kuake/music/pic/%E7%88%B1%E4%B8%AB%E7%88%B1%E4%B8%AB.jpg",
    "lrc": "https://openlist.ofxiv.qzz.io/d/kuake/music/lrc/%E7%88%B1%E4%B8%AB%E7%88%B1%E4%B8%AB.lrc",
    "filename": ""
  },
  {
    "name": "第六感 feat.東京ゲゲゲイ",
    "artist": "Reol/東京ゲゲゲイ",
    "url": "https://openlist.ofxiv.qzz.io/d/kuake/music/%E7%AC%AC%E5%85%AD%E6%84%9F%20feat.%E6%9D%B1%E4%BA%AC%E3%82%B2%E3%82%B2%E3%82%B2%E3%82%A4%20-%20Reol_%E6%9D%B1%E4%BA%AC%E3%82%B2%E3%82%B2%E3%82%B2%E3%82%A4.flac",
    "cover": "https://openlist.ofxiv.qzz.io/d/kuake/music/%E7%AC%AC%E5%85%AD%E6%84%9F%20feat.%E6%9D%B1%E4%BA%AC%E3%82%B2%E3%82%B2%E3%82%B2%E3%82%A4%20-%20Reol_%E6%9D%B1%E4%BA%AC%E3%82%B2%E3%82%B2%E3%82%B2%E3%82%A4.jpg",
    "lrc": "https://openlist.ofxiv.qzz.io/d/kuake/music/%E7%AC%AC%E5%85%AD%E6%84%9F%20feat.%E6%9D%B1%E4%BA%AC%E3%82%B2%E3%82%B2%E3%82%B2%E3%82%A4%20-%20Reol_%E6%9D%B1%E4%BA%AC%E3%82%B2%E3%82%B2%E3%82%B2%E3%82%A4.lrc",
    "filename": "第六感 feat.東京ゲゲゲイ - Reol_東京ゲゲゲイ"
  },
  {
    "name": "爱我还是他",
    "artist": "陶喆",
    "url": "https://openlist.ofxiv.qzz.io/d/kuake/music/%E7%88%B1%E6%88%91%E8%BF%98%E6%98%AF%E4%BB%96%20-%20%E9%99%B6%E5%96%86.flac",
    "cover": "https://openlist.ofxiv.qzz.io/d/kuake/music/%E7%88%B1%E6%88%91%E8%BF%98%E6%98%AF%E4%BB%96%20-%20%E9%99%B6%E5%96%86.jpg",
    "lrc": "https://openlist.ofxiv.qzz.io/d/kuake/music/%E7%88%B1%E6%88%91%E8%BF%98%E6%98%AF%E4%BB%96%20-%20%E9%99%B6%E5%96%86.lrc",
    "filename": "爱我还是他 - 陶喆"
  },
  {
    "name": "我怀念的",
    "artist": "AKA/wen酱",
    "url": "https://openlist.ofxiv.qzz.io/d/kuake/music/%E6%88%91%E6%80%80%E5%BF%B5%E7%9A%84%20-%20AKA_wen%E9%85%B1.flac",
    "cover": "https://openlist.ofxiv.qzz.io/d/kuake/music/%E6%88%91%E6%80%80%E5%BF%B5%E7%9A%84%20-%20AKA_wen%E9%85%B1.jpg",
    "lrc": "https://openlist.ofxiv.qzz.io/d/kuake/music/%E6%88%91%E6%80%80%E5%BF%B5%E7%9A%84%20-%20AKA_wen%E9%85%B1.lrc",
    "filename": "我怀念的 - AKA_wen酱"
  },
  {
    "name": "Symphony",
    "artist": "Donna Tella/Arc North",
    "url": "https://openlist.ofxiv.qzz.io/d/kuake/music/Symphony%20-%20Donna%20Tella_Arc%20North.flac",
    "cover": "https://openlist.ofxiv.qzz.io/d/kuake/music/Symphony%20-%20Donna%20Tella_Arc%20North.jpg",
    "lrc": "https://openlist.ofxiv.qzz.io/d/kuake/music/Symphony%20-%20Donna%20Tella_Arc%20North.lrc",
    "filename": "Symphony - Donna Tella_Arc North"
  },
  {
    "name": "Feel Good",
    "artist": "Gryffin/ILLENIUM/Daya",
    "url": "https://openlist.ofxiv.qzz.io/d/kuake/music/Feel%20Good%20-%20Gryffin_ILLENIUM_Daya.flac",
    "cover": "https://openlist.ofxiv.qzz.io/d/kuake/music/Feel%20Good%20-%20Gryffin_ILLENIUM_Daya.jpg",
    "lrc": "https://openlist.ofxiv.qzz.io/d/kuake/music/Feel%20Good%20-%20Gryffin_ILLENIUM_Daya.lrc",
    "filename": "Feel Good - Gryffin_ILLENIUM_Daya"
  },
  {
    "name": "晚安",
    "artist": "Joy",
    "url": "https://openlist.ofxiv.qzz.io/d/kuake/music/%E6%99%9A%E5%AE%89%20-%20Joy.flac",
    "cover": "https://openlist.ofxiv.qzz.io/d/kuake/music/%E6%99%9A%E5%AE%89%20-%20Joy.jpg",
    "lrc": "https://openlist.ofxiv.qzz.io/d/kuake/music/%E6%99%9A%E5%AE%89%20-%20Joy.lrc",
    "filename": "晚安 - Joy"
  },
  {
    "name": "这，就是爱",
    "artist": "张杰",
    "url": "https://openlist.ofxiv.qzz.io/d/kuake/music/%E8%BF%99%EF%BC%8C%E5%B0%B1%E6%98%AF%E7%88%B1%20-%20%E5%BC%A0%E6%9D%B0.flac",
    "cover": "https://openlist.ofxiv.qzz.io/d/kuake/music/%E8%BF%99%EF%BC%8C%E5%B0%B1%E6%98%AF%E7%88%B1%20-%20%E5%BC%A0%E6%9D%B0.jpg",
    "lrc": "https://openlist.ofxiv.qzz.io/d/kuake/music/%E8%BF%99%EF%BC%8C%E5%B0%B1%E6%98%AF%E7%88%B1%20-%20%E5%BC%A0%E6%9D%B0.lrc",
    "filename": "这，就是爱 - 张杰"
  },
  {
    "name": "安和桥",
    "artist": "宋冬野",
    "url": "https://openlist.ofxiv.qzz.io/d/kuake/music/%E5%AE%89%E5%92%8C%E6%A1%A5%20-%20%E5%AE%8B%E5%86%AC%E9%87%8E.flac",
    "cover": "https://openlist.ofxiv.qzz.io/d/kuake/music/%E5%AE%89%E5%92%8C%E6%A1%A5%20-%20%E5%AE%8B%E5%86%AC%E9%87%8E.jpg",
    "lrc": "https://openlist.ofxiv.qzz.io/d/kuake/music/%E5%AE%89%E5%92%8C%E6%A1%A5%20-%20%E5%AE%8B%E5%86%AC%E9%87%8E.lrc",
    "filename": "安和桥 - 宋冬野"
  },
  {
    "name": "Call of Silence",
    "artist": "澤野弘之/R!N/Gemie",
    "url": "https://openlist.ofxiv.qzz.io/d/kuake/music/Call%20of%20Silence%20-%20%E6%BE%A4%E9%87%8E%E5%BC%98%E4%B9%8B_R%21N_Gemie.flac",
    "cover": "https://openlist.ofxiv.qzz.io/d/kuake/music/Call%20of%20Silence%20-%20%E6%BE%A4%E9%87%8E%E5%BC%98%E4%B9%8B_R%21N_Gemie.jpg",
    "lrc": "https://openlist.ofxiv.qzz.io/d/kuake/music/Call%20of%20Silence%20-%20%E6%BE%A4%E9%87%8E%E5%BC%98%E4%B9%8B_R%21N_Gemie.lrc",
    "filename": "Call of Silence - 澤野弘之_R!N_Gemie"
  },
  {
    "name": "Outside",
    "artist": "Calvin Harris/Ellie Goulding",
    "url": "https://openlist.ofxiv.qzz.io/d/kuake/music/Outside%20-%20Calvin%20Harris_Ellie%20Goulding.flac",
    "cover": "https://openlist.ofxiv.qzz.io/d/kuake/music/Outside%20-%20Calvin%20Harris_Ellie%20Goulding.jpg",
    "lrc": "https://openlist.ofxiv.qzz.io/d/kuake/music/Outside%20-%20Calvin%20Harris_Ellie%20Goulding.lrc",
    "filename": "Outside - Calvin Harris_Ellie Goulding"
  },
  {
    "name": "No Matter What",
    "artist": "Bougenvilla/Albert Neve/David Puentez",
    "url": "https://openlist.ofxiv.qzz.io/d/kuake/music/No%20Matter%20What%20-%20Bougenvilla_Albert%20Neve_David%20Puentez.flac",
    "cover": "https://openlist.ofxiv.qzz.io/d/kuake/music/No%20Matter%20What%20-%20Bougenvilla_Albert%20Neve_David%20Puentez.jpg",
    "lrc": "https://openlist.ofxiv.qzz.io/d/kuake/music/No%20Matter%20What%20-%20Bougenvilla_Albert%20Neve_David%20Puentez.lrc",
    "filename": "No Matter What - Bougenvilla_Albert Neve_David Puentez"
  },
  {
    "name": "天若有情（女声版）",
    "artist": "高杰杰杰杰",
    "url": "https://openlist.ofxiv.qzz.io/d/kuake/music/%E5%A4%A9%E8%8B%A5%E6%9C%89%E6%83%85%EF%BC%88%E5%A5%B3%E5%A3%B0%E7%89%88%EF%BC%89%20-%20%E9%AB%98%E6%9D%B0%E6%9D%B0%E6%9D%B0%E6%9D%B0.flac",
    "cover": "https://openlist.ofxiv.qzz.io/d/kuake/music/%E5%A4%A9%E8%8B%A5%E6%9C%89%E6%83%85%EF%BC%88%E5%A5%B3%E5%A3%B0%E7%89%88%EF%BC%89%20-%20%E9%AB%98%E6%9D%B0%E6%9D%B0%E6%9D%B0%E6%9D%B0.jpg",
    "lrc": "https://openlist.ofxiv.qzz.io/d/kuake/music/%E5%A4%A9%E8%8B%A5%E6%9C%89%E6%83%85%EF%BC%88%E5%A5%B3%E5%A3%B0%E7%89%88%EF%BC%89%20-%20%E9%AB%98%E6%9D%B0%E6%9D%B0%E6%9D%B0%E6%9D%B0.lrc",
    "filename": "天若有情（女声版） - 高杰杰杰杰"
  }
]
